spotiparser/__init__.py
spotiparser/spotiparser.py
spotiparser-0.0.1.dist-info/LICENSE
spotiparser-0.0.1.dist-info/METADATA
spotiparser-0.0.1.dist-info/WHEEL
spotiparser-0.0.1.dist-info/top_level.txt
spotiparser-0.0.1.dist-info/RECORD
