Metadata-Version: 2.1
Name: spotiparser
Version: 0.0.1
Summary: Parse and analyze Spotify streaming data downloaded from the Spotify website in your Python code.
Home-page: https://github.com/spotify-data-parsing/spotiparser
Author: Oliver Goeken
Author-email: oliverdgoeken@gmail.com
License: UNKNOWN
Platform: UNKNOWN
Classifier: Programming Language :: Python :: 3.7
Classifier: License :: OSI Approved :: GNU General Public License v3 (GPLv3)
